{
  "parent": "minecraft:husbandry/plant_seed",
  "criteria": {
    "pat_potato": {
      "trigger": "quark:pat_potato"
    }
  },
  "display": {
    "announce_to_chat": true,
    "description": {
      "translate": "advancements.quark.pat_potato.description"
    },
    "frame": "task",
    "hidden": true,
    "icon": {
      "item": "quark:tiny_potato"
    },
    "show_toast": true,
    "title": {
      "translate": "advancements.quark.pat_potato.title"
    }
  },
  "requirements": [
    [
      "pat_potato"
    ]
  ],
  "conditions": [
    {
      "type": "quark:advancement_flag",
      "flag": "tiny_potato"
    }
  ]

}